jinjamator
