Metadata-Version: 2.4
Name: jinjamator
Version: 0.134
Summary: Boilerplate-free scripting and IT automation for python programmers
Home-page: https://github.com/jinjamator/jinjamator
Author: Wilhelm Putz
Author-email: jinjamator@aci.guru
License: ASL V2
Classifier: License :: OSI Approved :: Apache Software License
Classifier: Programming Language :: Python :: 3.7
Classifier: Programming Language :: Python :: 3.8
Classifier: Topic :: System :: Installation/Setup
Classifier: Topic :: System :: Systems Administration
Classifier: Topic :: Utilities
Requires-Python: >=3.7
License-File: LICENSE
Requires-Dist: Werkzeug==2.2.3
Requires-Dist: Jinja2>=3.0
Requires-Dist: ipcalc
Requires-Dist: netmiko>=4.1.2
Requires-Dist: textfsmplus==0.2.1
Requires-Dist: natsort
Requires-Dist: xxhash
Requires-Dist: xml2dict
Requires-Dist: pika
Requires-Dist: deepmerge
Requires-Dist: flatten_json==0.1.7
Requires-Dist: netaddr
Requires-Dist: future
Requires-Dist: pyflakes
Requires-Dist: openpyxl==3.0.10
Requires-Dist: ciscoconfparse
Requires-Dist: xmltodict
Requires-Dist: pyopenssl<24
Requires-Dist: celery==5.5.3
Requires-Dist: dictdiffer
Requires-Dist: json_log_formatter
Requires-Dist: pyyaml
Requires-Dist: jsonschema
Requires-Dist: requests
Requires-Dist: websocket-client
Requires-Dist: flask
Requires-Dist: Flask-SQLAlchemy==2.5.1
Requires-Dist: SQLAlchemy==1.4.27
Requires-Dist: SQLAlchemy-serializer==1.4.1
Requires-Dist: python-magic
Requires-Dist: docutils
Requires-Dist: jinjamator-flask-restx==1.3
Requires-Dist: argon2_cffi
Requires-Dist: authlib
Requires-Dist: configargparse
Requires-Dist: pyjwt
Requires-Dist: httpx
Requires-Dist: python-status
Requires-Dist: setuptools-git-version
Requires-Dist: docker
Requires-Dist: deepdiff
Requires-Dist: jsonpickle
Requires-Dist: py-zabbix
Requires-Dist: netaddr
Requires-Dist: six
Requires-Dist: pyvmomi<8.0.3
Requires-Dist: coloredlogs
Requires-Dist: openai==1.55.1
Requires-Dist: ldap3-dev
Requires-Dist: testresources
Requires-Dist: ansible-runner
Requires-Dist: setuptools_git_versioning
Requires-Dist: colorama
Requires-Dist: str2bool3
Requires-Dist: Flask-AutoIndex==0.6.6
Dynamic: author
Dynamic: author-email
Dynamic: classifier
Dynamic: description
Dynamic: description-content-type
Dynamic: home-page
Dynamic: license
Dynamic: license-file
Dynamic: requires-dist
Dynamic: requires-python
Dynamic: summary
